gpu_pca/__init__.py
gpu_pca/pca_module.py
tests/__init__.py
tests/benchmark_gpu_pca.py
tests/test_gpu_pca.py
PCAonGPU-0.1.dist-info/LICENSE
PCAonGPU-0.1.dist-info/METADATA
PCAonGPU-0.1.dist-info/WHEEL
PCAonGPU-0.1.dist-info/top_level.txt
PCAonGPU-0.1.dist-info/RECORD
