Metadata-Version: 2.1
Name: PCAonGPU
Version: 0.1
Summary: A GPU-based Incremental PCA implementation.
Home-page: https://github.com/dnhkng/PCAonGPU
Author: Your Name
Author-email: dnhkng@gmail.com
Classifier: Programming Language :: Python :: 3
Classifier: License :: OSI Approved :: MIT License
Classifier: Operating System :: OS Independent
Requires-Python: >=3.10
License-File: LICENSE
Requires-Dist: torch >=2.1.0
Provides-Extra: test
Requires-Dist: pytest >=1.3.2 ; extra == 'test'
Requires-Dist: scikit-learn >=1.3.2 ; extra == 'test'
Requires-Dist: numpy >=1.3.2 ; extra == 'test'
